apis/__init__.py
apis/admin.py
apis/apps.py
apis/models.py
apis/serializers.py
apis/tests.py
apis/urls.py
apis/views.py
apis/migrations/__init__.py
database_report/__init__.py
database_report/admin.py
database_report/apps.py
database_report/models.py
database_report/tests.py
database_report/urls.py
database_report/views.py
database_report/migrations/0001_initial.py
database_report/migrations/__init__.py
health_report/__init__.py
health_report/asgi.py
health_report/settings.py
health_report/urls.py
health_report/views.py
health_report/wsgi.py
health_report_pkg/__init__.py
health_report_pkg/cli.py
login_app/__init__.py
login_app/admin.py
login_app/apps.py
login_app/forms.py
login_app/models.py
login_app/tests.py
login_app/urls.py
login_app/views.py
login_app/migrations/0001_initial.py
login_app/migrations/0002_alter_odoosetup_url.py
login_app/migrations/__init__.py
system_report/__init__.py
system_report/admin.py
system_report/apps.py
system_report/methods.py
system_report/models.py
system_report/tests.py
system_report/urls.py
system_report/views.py
system_report/migrations/0001_initial.py
system_report/migrations/__init__.py
health_report_server_demo-0.1.0.dist-info/METADATA
health_report_server_demo-0.1.0.dist-info/WHEEL
health_report_server_demo-0.1.0.dist-info/entry_points.txt
health_report_server_demo-0.1.0.dist-info/top_level.txt
health_report_server_demo-0.1.0.dist-info/RECORD
